spotondocker/__init__.py
spotondocker/client.py
spotondocker/server.py
spotondocker/genpy/__init__.py
spotondocker/genpy/spotondocker/SpotOnDocker.py
spotondocker/genpy/spotondocker/__init__.py
spotondocker/genpy/spotondocker/constants.py
spotondocker/genpy/spotondocker/ttypes.py
spotondocker-0.1.2.dist-info/LICENSE
spotondocker-0.1.2.dist-info/METADATA
spotondocker-0.1.2.dist-info/WHEEL
spotondocker-0.1.2.dist-info/top_level.txt
spotondocker-0.1.2.dist-info/RECORD
