Metadata-Version: 2.1
Name: spotondocker
Version: 0.1.2
Summary: SpotOnDocker is a utility which exposes some of spot (spot.lrde.epita.fr) functionality as a dockerized service.
Home-page: https://github.com/abhibp1993/spotondocker
Author: Abhishek N. Kulkarni
Author-email: abhibp1993@gmail.com
License: UNKNOWN
Platform: UNKNOWN
Classifier: Development Status :: 2 - Pre-Alpha
Classifier: Intended Audience :: Science/Research
Classifier: Programming Language :: Python :: 3
Classifier: License :: OSI Approved :: BSD License
Classifier: Operating System :: OS Independent
Classifier: Topic :: Software Development :: Libraries :: Python Modules
Classifier: Topic :: Scientific/Engineering :: Mathematics
Classifier: Topic :: Scientific/Engineering :: Artificial Intelligence
Requires-Python: >=3.7
